MANIFEST.in
VERSION
setup.py
canonical.ext.datasets.egg-info/PKG-INFO
canonical.ext.datasets.egg-info/SOURCES.txt
canonical.ext.datasets.egg-info/dependency_links.txt
canonical.ext.datasets.egg-info/requires.txt
canonical.ext.datasets.egg-info/top_level.txt
canonical/ext/datasets/__init__.py
canonical/ext/datasets/dataset.py
canonical/ext/datasets/package.json