Metadata-Version: 2.1
Name: canonical.ext.datasets
Version: 0.0.4
Summary: Typed datasets using the Hugging Face datasets library
Home-page: https://gitlab.com/unimatrixone
Author: Cochise Ruhulessin
Author-email: cochiseruhulessin@gmail.com
Classifier: Development Status :: 4 - Beta
Classifier: Intended Audience :: Developers
Classifier: License :: OSI Approved :: MIT License
Classifier: Operating System :: POSIX
Classifier: Operating System :: POSIX :: Linux
Classifier: Programming Language :: Python :: 3.11
Classifier: Programming Language :: Python :: 3.12
Classifier: Programming Language :: Python :: 3 :: Only
Classifier: Topic :: Software Development :: Libraries
Requires-Dist: datasets
Requires-Dist: pydantic>=2
